qiu_mcp_demo/__init__.py
qiu_mcp_demo-0.1.0.dist-info/WHEEL
qiu_mcp_demo-0.1.0.dist-info/entry_points.txt
qiu_mcp_demo-0.1.0.dist-info/METADATA
qiu_mcp_demo-0.1.0.dist-info/RECORD
