Metadata-Version: 2.3
Name: qiu-mcp-demo
Version: 0.1.0
Summary: Add your description here
Author: qiuhao0107
Author-email: qiuhao0107 <2245066631@qq.com>
Requires-Dist: mcp[cli]>=1.13.1
Requires-Python: >=3.13
